resif_delivery_stats_plotter/__init__.py
resif_delivery_stats_plotter/cli.py
resif_delivery_stats_plotter/errors.py
resif_delivery_stats_plotter/assets/bootstrap.bundle.min.js
resif_delivery_stats_plotter/assets/bootstrap.min.css
resif_delivery_stats_plotter/assets/jquery-3.5.1.slim.min.js
resif_delivery_stats_plotter/assets/jquery.dataTables.min.css
resif_delivery_stats_plotter/assets/jquery.dataTables.min.js
resif_delivery_stats_plotter/assets/plotly-latest.min.js
resif_delivery_stats_plotter/assets/resif_logo.png
resif_delivery_stats_plotter/assets/triangle-10.png
resif_delivery_stats_plotter/assets/triangle-15.png
resif_delivery_stats_plotter/assets/triangle-20.png
resif_delivery_stats_plotter/assets/triangle-25.png
resif_delivery_stats_plotter/assets/triangle-5.png
resif_delivery_stats_plotter/assets/triangle.png
resif_delivery_stats_plotter/factories/__init__.py
resif_delivery_stats_plotter/factories/channel.py
resif_delivery_stats_plotter/factories/enums.py
resif_delivery_stats_plotter/factories/network.py
resif_delivery_stats_plotter/factories/plotter.py
resif_delivery_stats_plotter/factories/report.py
resif_delivery_stats_plotter/factories/station.py
resif_delivery_stats_plotter/models/__init__.py
resif_delivery_stats_plotter/models/channel.py
resif_delivery_stats_plotter/models/enums.py
resif_delivery_stats_plotter/models/mixins.py
resif_delivery_stats_plotter/models/network.py
resif_delivery_stats_plotter/models/report.py
resif_delivery_stats_plotter/models/station.py
resif_delivery_stats_plotter/services/__init__.py
resif_delivery_stats_plotter/services/clients/__init__.py
resif_delivery_stats_plotter/services/clients/availabilty.py
resif_delivery_stats_plotter/services/clients/statistics.py
resif_delivery_stats_plotter/services/plotters/__init__.py
resif_delivery_stats_plotter/services/plotters/html.py
resif_delivery_stats_plotter/services/plotters/png.py
resif_delivery_stats_plotter/services/report_builders/__init__.py
resif_delivery_stats_plotter-0.1.3.dist-info/LICENSE.txt
resif_delivery_stats_plotter-0.1.3.dist-info/METADATA
resif_delivery_stats_plotter-0.1.3.dist-info/WHEEL
resif_delivery_stats_plotter-0.1.3.dist-info/entry_points.txt
resif_delivery_stats_plotter-0.1.3.dist-info/top_level.txt
resif_delivery_stats_plotter-0.1.3.dist-info/RECORD
