Metadata-Version: 2.1
Name: resif-delivery-stats-plotter
Version: 0.1.3
Summary: Résif Delivery stats plotter
Home-page: https://gitlab.com/resif/resif-delivery-stats-plotter
Author: Philippe Bollard
Author-email: philippe.bollard@univ-grenoble-alpes.fr
Maintainer: Philippe Bollard
Maintainer-email: philippe.bollard@univ-grenoble-alpes.fr
License: GPLv3
Platform: UNKNOWN
Classifier: Development Status :: 4 - Beta
Classifier: Intended Audience :: Developers
Classifier: License :: OSI Approved :: GNU General Public License v3 (GPLv3)
Classifier: Natural Language :: English
Classifier: Operating System :: OS Independent
Classifier: Programming Language :: Python :: 3
Requires-Dist: click
Requires-Dist: click-log
Requires-Dist: obspy
Requires-Dist: requests-cache
Requires-Dist: ordered-enum
Requires-Dist: arrow
Requires-Dist: DateTimeRange
Requires-Dist: jinja2
Requires-Dist: pint
Requires-Dist: matplotlib
Requires-Dist: pandas
Requires-Dist: iso3166
Requires-Dist: staticmap
Requires-Dist: geopandas
Requires-Dist: descartes
